setup.py
supermodule/__init__.py
supermodule/superdupermodule.py
supermodule.egg-info/PKG-INFO
supermodule.egg-info/SOURCES.txt
supermodule.egg-info/dependency_links.txt
supermodule.egg-info/top_level.txt