Metadata-Version: 1.0
Name: supermodule
Version: 2018.1.21.158
Summary: super utilities
Home-page: https://github.com/wdbm/junk
Author: John Drake
Author-email: j.drake@sern.ch
License: GPLv3
Platform: UNKNOWN
